adapter_transformers/__init__.py
adapter_transformers/activations.py
adapter_transformers/activations_tf.py
adapter_transformers/configuration_utils.py
adapter_transformers/convert_graph_to_onnx.py
adapter_transformers/convert_pytorch_checkpoint_to_tf2.py
adapter_transformers/convert_slow_tokenizer.py
adapter_transformers/convert_slow_tokenizers_checkpoints_to_fast.py
adapter_transformers/convert_tf_hub_seq_to_seq_bert_to_pytorch.py
adapter_transformers/debug_utils.py
adapter_transformers/deepspeed.py
adapter_transformers/dependency_versions_check.py
adapter_transformers/dependency_versions_table.py
adapter_transformers/dynamic_module_utils.py
adapter_transformers/feature_extraction_sequence_utils.py
adapter_transformers/feature_extraction_utils.py
adapter_transformers/file_utils.py
adapter_transformers/generation_beam_constraints.py
adapter_transformers/generation_beam_search.py
adapter_transformers/generation_flax_logits_process.py
adapter_transformers/generation_flax_utils.py
adapter_transformers/generation_logits_process.py
adapter_transformers/generation_stopping_criteria.py
adapter_transformers/generation_tf_logits_process.py
adapter_transformers/generation_tf_utils.py
adapter_transformers/generation_utils.py
adapter_transformers/hf_argparser.py
adapter_transformers/image_utils.py
adapter_transformers/integrations.py
adapter_transformers/keras_callbacks.py
adapter_transformers/modelcard.py
adapter_transformers/modeling_flax_outputs.py
adapter_transformers/modeling_flax_pytorch_utils.py
adapter_transformers/modeling_flax_utils.py
adapter_transformers/modeling_outputs.py
adapter_transformers/modeling_tf_outputs.py
adapter_transformers/modeling_tf_pytorch_utils.py
adapter_transformers/modeling_tf_utils.py
adapter_transformers/modeling_utils.py
adapter_transformers/optimization.py
adapter_transformers/optimization_tf.py
adapter_transformers/processing_utils.py
adapter_transformers/py.typed
adapter_transformers/pytorch_utils.py
cody_adapter_transformers-3.0.1.dist-info/LICENSE
cody_adapter_transformers-3.0.1.dist-info/METADATA
cody_adapter_transformers-3.0.1.dist-info/WHEEL
cody_adapter_transformers-3.0.1.dist-info/top_level.txt
cody_adapter_transformers-3.0.1.dist-info/RECORD
