Metadata-Version: 2.1
Name: cody-adapter-transformers
Version: 3.0.1
Summary: A friendly fork of HuggingFace's Transformers, adding Adapters to PyTorch language models
Home-page: https://github.com/adapter-hub/adapter-transformers
Author: Jonas Pfeiffer, Andreas Rücklé, Clifton Poth, Hannah Sterz, based on work by the HuggingFace team and community
Author-email: pfeiffer@ukp.tu-darmstadt.de
License: Apache
Keywords: NLP deep learning transformer pytorch BERT adapters
Platform: UNKNOWN
Classifier: Development Status :: 5 - Production/Stable
Classifier: Intended Audience :: Developers
Classifier: Intended Audience :: Education
Classifier: Intended Audience :: Science/Research
Classifier: License :: OSI Approved :: Apache Software License
Classifier: Operating System :: OS Independent
Classifier: Programming Language :: Python :: 3
Classifier: Programming Language :: Python :: 3.6
Classifier: Programming Language :: Python :: 3.7
Classifier: Programming Language :: Python :: 3.8
Classifier: Programming Language :: Python :: 3.9
Classifier: Topic :: Scientific/Engineering :: Artificial Intelligence
Requires-Python: >=3.6.0
Requires-Dist: filelock
Requires-Dist: huggingface-hub (<1.0,>=0.1.0)
Requires-Dist: numpy (>=1.17)
Requires-Dist: packaging (>=20.0)
Requires-Dist: pyyaml (>=5.1)
Requires-Dist: regex (!=2019.12.17)
Requires-Dist: requests
Requires-Dist: sacremoses
Requires-Dist: tokenizers (!=0.11.3,>=0.11.1)
Requires-Dist: tqdm (>=4.27)
Requires-Dist: dataclasses ; python_version < "3.7"
Requires-Dist: importlib-metadata ; python_version < "3.8"
Provides-Extra: all
Requires-Dist: tensorflow (>=2.3) ; extra == 'all'
Requires-Dist: onnxconverter-common ; extra == 'all'
Requires-Dist: tf2onnx ; extra == 'all'
Requires-Dist: torch (>=1.0) ; extra == 'all'
Requires-Dist: jax (>=0.2.8) ; extra == 'all'
Requires-Dist: jaxlib (>=0.1.65) ; extra == 'all'
Requires-Dist: flax (>=0.3.5) ; extra == 'all'
Requires-Dist: optax (>=0.0.8) ; extra == 'all'
Requires-Dist: sentencepiece (!=0.1.92,>=0.1.91) ; extra == 'all'
Requires-Dist: protobuf ; extra == 'all'
Requires-Dist: tokenizers (!=0.11.3,>=0.11.1) ; extra == 'all'
Requires-Dist: torchaudio ; extra == 'all'
Requires-Dist: librosa ; extra == 'all'
Requires-Dist: pyctcdecode (>=0.3.0) ; extra == 'all'
Requires-Dist: phonemizer ; extra == 'all'
Requires-Dist: Pillow ; extra == 'all'
Requires-Dist: optuna ; extra == 'all'
Requires-Dist: ray[tune] ; extra == 'all'
Requires-Dist: sigopt ; extra == 'all'
Requires-Dist: timm ; extra == 'all'
Requires-Dist: codecarbon (==1.2.0) ; extra == 'all'
Provides-Extra: audio
Requires-Dist: librosa ; extra == 'audio'
Requires-Dist: pyctcdecode (>=0.3.0) ; extra == 'audio'
Requires-Dist: phonemizer ; extra == 'audio'
Provides-Extra: codecarbon
Requires-Dist: codecarbon (==1.2.0) ; extra == 'codecarbon'
Provides-Extra: deepspeed
Requires-Dist: deepspeed (>=0.5.9) ; extra == 'deepspeed'
Provides-Extra: dev
Requires-Dist: tensorflow (>=2.3) ; extra == 'dev'
Requires-Dist: onnxconverter-common ; extra == 'dev'
Requires-Dist: tf2onnx ; extra == 'dev'
Requires-Dist: torch (>=1.0) ; extra == 'dev'
Requires-Dist: jax (>=0.2.8) ; extra == 'dev'
Requires-Dist: jaxlib (>=0.1.65) ; extra == 'dev'
Requires-Dist: flax (>=0.3.5) ; extra == 'dev'
Requires-Dist: optax (>=0.0.8) ; extra == 'dev'
Requires-Dist: sentencepiece (!=0.1.92,>=0.1.91) ; extra == 'dev'
Requires-Dist: protobuf ; extra == 'dev'
Requires-Dist: tokenizers (!=0.11.3,>=0.11.1) ; extra == 'dev'
Requires-Dist: torchaudio ; extra == 'dev'
Requires-Dist: librosa ; extra == 'dev'
Requires-Dist: pyctcdecode (>=0.3.0) ; extra == 'dev'
Requires-Dist: phonemizer ; extra == 'dev'
Requires-Dist: Pillow ; extra == 'dev'
Requires-Dist: optuna ; extra == 'dev'
Requires-Dist: ray[tune] ; extra == 'dev'
Requires-Dist: sigopt ; extra == 'dev'
Requires-Dist: timm ; extra == 'dev'
Requires-Dist: codecarbon (==1.2.0) ; extra == 'dev'
Requires-Dist: pytest ; extra == 'dev'
Requires-Dist: pytest-xdist ; extra == 'dev'
Requires-Dist: timeout-decorator ; extra == 'dev'
Requires-Dist: parameterized ; extra == 'dev'
Requires-Dist: psutil ; extra == 'dev'
Requires-Dist: datasets ; extra == 'dev'
Requires-Dist: pytest-timeout ; extra == 'dev'
Requires-Dist: black (~=22.0) ; extra == 'dev'
Requires-Dist: sacrebleu (<2.0.0,>=1.4.12) ; extra == 'dev'
Requires-Dist: rouge-score ; extra == 'dev'
Requires-Dist: nltk ; extra == 'dev'
Requires-Dist: GitPython (<3.1.19) ; extra == 'dev'
Requires-Dist: faiss-cpu ; extra == 'dev'
Requires-Dist: cookiecutter (==1.7.2) ; extra == 'dev'
Requires-Dist: isort (>=5.5.4) ; extra == 'dev'
Requires-Dist: flake8 (>=3.8.3) ; extra == 'dev'
Requires-Dist: fugashi (>=1.0) ; extra == 'dev'
Requires-Dist: ipadic (<2.0,>=1.0.0) ; extra == 'dev'
Requires-Dist: unidic-lite (>=1.0.7) ; extra == 'dev'
Requires-Dist: unidic (>=1.0.2) ; extra == 'dev'
Requires-Dist: docutils (==0.16.0) ; extra == 'dev'
Requires-Dist: myst-parser ; extra == 'dev'
Requires-Dist: sphinx (==3.2.1) ; extra == 'dev'
Requires-Dist: sphinx-markdown-tables ; extra == 'dev'
Requires-Dist: sphinx-rtd-theme (==0.4.3) ; extra == 'dev'
Requires-Dist: sphinx-copybutton ; extra == 'dev'
Requires-Dist: sphinxext-opengraph (==0.4.1) ; extra == 'dev'
Requires-Dist: sphinx-intl ; extra == 'dev'
Requires-Dist: sphinx-multiversion ; extra == 'dev'
Requires-Dist: scikit-learn ; extra == 'dev'
Provides-Extra: dev-tensorflow
Requires-Dist: pytest ; extra == 'dev-tensorflow'
Requires-Dist: pytest-xdist ; extra == 'dev-tensorflow'
Requires-Dist: timeout-decorator ; extra == 'dev-tensorflow'
Requires-Dist: parameterized ; extra == 'dev-tensorflow'
Requires-Dist: psutil ; extra == 'dev-tensorflow'
Requires-Dist: datasets ; extra == 'dev-tensorflow'
Requires-Dist: pytest-timeout ; extra == 'dev-tensorflow'
Requires-Dist: black (~=22.0) ; extra == 'dev-tensorflow'
Requires-Dist: sacrebleu (<2.0.0,>=1.4.12) ; extra == 'dev-tensorflow'
Requires-Dist: rouge-score ; extra == 'dev-tensorflow'
Requires-Dist: nltk ; extra == 'dev-tensorflow'
Requires-Dist: GitPython (<3.1.19) ; extra == 'dev-tensorflow'
Requires-Dist: faiss-cpu ; extra == 'dev-tensorflow'
Requires-Dist: cookiecutter (==1.7.2) ; extra == 'dev-tensorflow'
Requires-Dist: tensorflow (>=2.3) ; extra == 'dev-tensorflow'
Requires-Dist: onnxconverter-common ; extra == 'dev-tensorflow'
Requires-Dist: tf2onnx ; extra == 'dev-tensorflow'
Requires-Dist: sentencepiece (!=0.1.92,>=0.1.91) ; extra == 'dev-tensorflow'
Requires-Dist: protobuf ; extra == 'dev-tensorflow'
Requires-Dist: tokenizers (!=0.11.3,>=0.11.1) ; extra == 'dev-tensorflow'
Requires-Dist: Pillow ; extra == 'dev-tensorflow'
Requires-Dist: isort (>=5.5.4) ; extra == 'dev-tensorflow'
Requires-Dist: flake8 (>=3.8.3) ; extra == 'dev-tensorflow'
Requires-Dist: docutils (==0.16.0) ; extra == 'dev-tensorflow'
Requires-Dist: myst-parser ; extra == 'dev-tensorflow'
Requires-Dist: sphinx (==3.2.1) ; extra == 'dev-tensorflow'
Requires-Dist: sphinx-markdown-tables ; extra == 'dev-tensorflow'
Requires-Dist: sphinx-rtd-theme (==0.4.3) ; extra == 'dev-tensorflow'
Requires-Dist: sphinx-copybutton ; extra == 'dev-tensorflow'
Requires-Dist: sphinxext-opengraph (==0.4.1) ; extra == 'dev-tensorflow'
Requires-Dist: sphinx-intl ; extra == 'dev-tensorflow'
Requires-Dist: sphinx-multiversion ; extra == 'dev-tensorflow'
Requires-Dist: scikit-learn ; extra == 'dev-tensorflow'
Requires-Dist: onnxruntime (>=1.4.0) ; extra == 'dev-tensorflow'
Requires-Dist: onnxruntime-tools (>=1.4.2) ; extra == 'dev-tensorflow'
Requires-Dist: librosa ; extra == 'dev-tensorflow'
Requires-Dist: pyctcdecode (>=0.3.0) ; extra == 'dev-tensorflow'
Requires-Dist: phonemizer ; extra == 'dev-tensorflow'
Provides-Extra: dev-torch
Requires-Dist: pytest ; extra == 'dev-torch'
Requires-Dist: pytest-xdist ; extra == 'dev-torch'
Requires-Dist: timeout-decorator ; extra == 'dev-torch'
Requires-Dist: parameterized ; extra == 'dev-torch'
Requires-Dist: psutil ; extra == 'dev-torch'
Requires-Dist: datasets ; extra == 'dev-torch'
Requires-Dist: pytest-timeout ; extra == 'dev-torch'
Requires-Dist: black (~=22.0) ; extra == 'dev-torch'
Requires-Dist: sacrebleu (<2.0.0,>=1.4.12) ; extra == 'dev-torch'
Requires-Dist: rouge-score ; extra == 'dev-torch'
Requires-Dist: nltk ; extra == 'dev-torch'
Requires-Dist: GitPython (<3.1.19) ; extra == 'dev-torch'
Requires-Dist: faiss-cpu ; extra == 'dev-torch'
Requires-Dist: cookiecutter (==1.7.2) ; extra == 'dev-torch'
Requires-Dist: torch (>=1.0) ; extra == 'dev-torch'
Requires-Dist: sentencepiece (!=0.1.92,>=0.1.91) ; extra == 'dev-torch'
Requires-Dist: protobuf ; extra == 'dev-torch'
Requires-Dist: tokenizers (!=0.11.3,>=0.11.1) ; extra == 'dev-torch'
Requires-Dist: torchaudio ; extra == 'dev-torch'
Requires-Dist: librosa ; extra == 'dev-torch'
Requires-Dist: pyctcdecode (>=0.3.0) ; extra == 'dev-torch'
Requires-Dist: phonemizer ; extra == 'dev-torch'
Requires-Dist: Pillow ; extra == 'dev-torch'
Requires-Dist: optuna ; extra == 'dev-torch'
Requires-Dist: ray[tune] ; extra == 'dev-torch'
Requires-Dist: sigopt ; extra == 'dev-torch'
Requires-Dist: timm ; extra == 'dev-torch'
Requires-Dist: codecarbon (==1.2.0) ; extra == 'dev-torch'
Requires-Dist: isort (>=5.5.4) ; extra == 'dev-torch'
Requires-Dist: flake8 (>=3.8.3) ; extra == 'dev-torch'
Requires-Dist: fugashi (>=1.0) ; extra == 'dev-torch'
Requires-Dist: ipadic (<2.0,>=1.0.0) ; extra == 'dev-torch'
Requires-Dist: unidic-lite (>=1.0.7) ; extra == 'dev-torch'
Requires-Dist: unidic (>=1.0.2) ; extra == 'dev-torch'
Requires-Dist: docutils (==0.16.0) ; extra == 'dev-torch'
Requires-Dist: myst-parser ; extra == 'dev-torch'
Requires-Dist: sphinx (==3.2.1) ; extra == 'dev-torch'
Requires-Dist: sphinx-markdown-tables ; extra == 'dev-torch'
Requires-Dist: sphinx-rtd-theme (==0.4.3) ; extra == 'dev-torch'
Requires-Dist: sphinx-copybutton ; extra == 'dev-torch'
Requires-Dist: sphinxext-opengraph (==0.4.1) ; extra == 'dev-torch'
Requires-Dist: sphinx-intl ; extra == 'dev-torch'
Requires-Dist: sphinx-multiversion ; extra == 'dev-torch'
Requires-Dist: scikit-learn ; extra == 'dev-torch'
Requires-Dist: onnxruntime (>=1.4.0) ; extra == 'dev-torch'
Requires-Dist: onnxruntime-tools (>=1.4.2) ; extra == 'dev-torch'
Provides-Extra: docs
Requires-Dist: tensorflow (>=2.3) ; extra == 'docs'
Requires-Dist: onnxconverter-common ; extra == 'docs'
Requires-Dist: tf2onnx ; extra == 'docs'
Requires-Dist: torch (>=1.0) ; extra == 'docs'
Requires-Dist: jax (>=0.2.8) ; extra == 'docs'
Requires-Dist: jaxlib (>=0.1.65) ; extra == 'docs'
Requires-Dist: flax (>=0.3.5) ; extra == 'docs'
Requires-Dist: optax (>=0.0.8) ; extra == 'docs'
Requires-Dist: sentencepiece (!=0.1.92,>=0.1.91) ; extra == 'docs'
Requires-Dist: protobuf ; extra == 'docs'
Requires-Dist: tokenizers (!=0.11.3,>=0.11.1) ; extra == 'docs'
Requires-Dist: torchaudio ; extra == 'docs'
Requires-Dist: librosa ; extra == 'docs'
Requires-Dist: pyctcdecode (>=0.3.0) ; extra == 'docs'
Requires-Dist: phonemizer ; extra == 'docs'
Requires-Dist: Pillow ; extra == 'docs'
Requires-Dist: optuna ; extra == 'docs'
Requires-Dist: ray[tune] ; extra == 'docs'
Requires-Dist: sigopt ; extra == 'docs'
Requires-Dist: timm ; extra == 'docs'
Requires-Dist: codecarbon (==1.2.0) ; extra == 'docs'
Requires-Dist: docutils (==0.16.0) ; extra == 'docs'
Requires-Dist: myst-parser ; extra == 'docs'
Requires-Dist: sphinx (==3.2.1) ; extra == 'docs'
Requires-Dist: sphinx-markdown-tables ; extra == 'docs'
Requires-Dist: sphinx-rtd-theme (==0.4.3) ; extra == 'docs'
Requires-Dist: sphinx-copybutton ; extra == 'docs'
Requires-Dist: sphinxext-opengraph (==0.4.1) ; extra == 'docs'
Requires-Dist: sphinx-intl ; extra == 'docs'
Requires-Dist: sphinx-multiversion ; extra == 'docs'
Provides-Extra: docs_specific
Requires-Dist: docutils (==0.16.0) ; extra == 'docs_specific'
Requires-Dist: myst-parser ; extra == 'docs_specific'
Requires-Dist: sphinx (==3.2.1) ; extra == 'docs_specific'
Requires-Dist: sphinx-markdown-tables ; extra == 'docs_specific'
Requires-Dist: sphinx-rtd-theme (==0.4.3) ; extra == 'docs_specific'
Requires-Dist: sphinx-copybutton ; extra == 'docs_specific'
Requires-Dist: sphinxext-opengraph (==0.4.1) ; extra == 'docs_specific'
Requires-Dist: sphinx-intl ; extra == 'docs_specific'
Requires-Dist: sphinx-multiversion ; extra == 'docs_specific'
Provides-Extra: fairscale
Requires-Dist: fairscale (>0.3) ; extra == 'fairscale'
Provides-Extra: flax
Requires-Dist: jax (>=0.2.8) ; extra == 'flax'
Requires-Dist: jaxlib (>=0.1.65) ; extra == 'flax'
Requires-Dist: flax (>=0.3.5) ; extra == 'flax'
Requires-Dist: optax (>=0.0.8) ; extra == 'flax'
Provides-Extra: flax-speech
Requires-Dist: librosa ; extra == 'flax-speech'
Requires-Dist: pyctcdecode (>=0.3.0) ; extra == 'flax-speech'
Requires-Dist: phonemizer ; extra == 'flax-speech'
Provides-Extra: ftfy
Requires-Dist: ftfy ; extra == 'ftfy'
Provides-Extra: integrations
Requires-Dist: optuna ; extra == 'integrations'
Requires-Dist: ray[tune] ; extra == 'integrations'
Requires-Dist: sigopt ; extra == 'integrations'
Provides-Extra: ja
Requires-Dist: fugashi (>=1.0) ; extra == 'ja'
Requires-Dist: ipadic (<2.0,>=1.0.0) ; extra == 'ja'
Requires-Dist: unidic-lite (>=1.0.7) ; extra == 'ja'
Requires-Dist: unidic (>=1.0.2) ; extra == 'ja'
Provides-Extra: modelcreation
Requires-Dist: cookiecutter (==1.7.2) ; extra == 'modelcreation'
Provides-Extra: onnx
Requires-Dist: onnxconverter-common ; extra == 'onnx'
Requires-Dist: tf2onnx ; extra == 'onnx'
Requires-Dist: onnxruntime (>=1.4.0) ; extra == 'onnx'
Requires-Dist: onnxruntime-tools (>=1.4.2) ; extra == 'onnx'
Provides-Extra: onnxruntime
Requires-Dist: onnxruntime (>=1.4.0) ; extra == 'onnxruntime'
Requires-Dist: onnxruntime-tools (>=1.4.2) ; extra == 'onnxruntime'
Provides-Extra: optuna
Requires-Dist: optuna ; extra == 'optuna'
Provides-Extra: quality
Requires-Dist: black (~=22.0) ; extra == 'quality'
Requires-Dist: isort (>=5.5.4) ; extra == 'quality'
Requires-Dist: flake8 (>=3.8.3) ; extra == 'quality'
Requires-Dist: GitPython (<3.1.19) ; extra == 'quality'
Provides-Extra: ray
Requires-Dist: ray[tune] ; extra == 'ray'
Provides-Extra: retrieval
Requires-Dist: faiss-cpu ; extra == 'retrieval'
Requires-Dist: datasets ; extra == 'retrieval'
Provides-Extra: sagemaker
Requires-Dist: sagemaker (>=2.31.0) ; extra == 'sagemaker'
Provides-Extra: sentencepiece
Requires-Dist: sentencepiece (!=0.1.92,>=0.1.91) ; extra == 'sentencepiece'
Requires-Dist: protobuf ; extra == 'sentencepiece'
Provides-Extra: serving
Requires-Dist: pydantic ; extra == 'serving'
Requires-Dist: uvicorn ; extra == 'serving'
Requires-Dist: fastapi ; extra == 'serving'
Requires-Dist: starlette ; extra == 'serving'
Provides-Extra: sigopt
Requires-Dist: sigopt ; extra == 'sigopt'
Provides-Extra: sklearn
Requires-Dist: scikit-learn ; extra == 'sklearn'
Provides-Extra: speech
Requires-Dist: torchaudio ; extra == 'speech'
Requires-Dist: librosa ; extra == 'speech'
Requires-Dist: pyctcdecode (>=0.3.0) ; extra == 'speech'
Requires-Dist: phonemizer ; extra == 'speech'
Provides-Extra: testing
Requires-Dist: pytest ; extra == 'testing'
Requires-Dist: pytest-xdist ; extra == 'testing'
Requires-Dist: timeout-decorator ; extra == 'testing'
Requires-Dist: parameterized ; extra == 'testing'
Requires-Dist: psutil ; extra == 'testing'
Requires-Dist: datasets ; extra == 'testing'
Requires-Dist: pytest-timeout ; extra == 'testing'
Requires-Dist: black (~=22.0) ; extra == 'testing'
Requires-Dist: sacrebleu (<2.0.0,>=1.4.12) ; extra == 'testing'
Requires-Dist: rouge-score ; extra == 'testing'
Requires-Dist: nltk ; extra == 'testing'
Requires-Dist: GitPython (<3.1.19) ; extra == 'testing'
Requires-Dist: faiss-cpu ; extra == 'testing'
Requires-Dist: cookiecutter (==1.7.2) ; extra == 'testing'
Provides-Extra: tf
Requires-Dist: tensorflow (>=2.3) ; extra == 'tf'
Requires-Dist: onnxconverter-common ; extra == 'tf'
Requires-Dist: tf2onnx ; extra == 'tf'
Provides-Extra: tf-cpu
Requires-Dist: tensorflow-cpu (>=2.3) ; extra == 'tf-cpu'
Requires-Dist: onnxconverter-common ; extra == 'tf-cpu'
Requires-Dist: tf2onnx ; extra == 'tf-cpu'
Provides-Extra: tf-speech
Requires-Dist: librosa ; extra == 'tf-speech'
Requires-Dist: pyctcdecode (>=0.3.0) ; extra == 'tf-speech'
Requires-Dist: phonemizer ; extra == 'tf-speech'
Provides-Extra: timm
Requires-Dist: timm ; extra == 'timm'
Provides-Extra: tokenizers
Requires-Dist: tokenizers (!=0.11.3,>=0.11.1) ; extra == 'tokenizers'
Provides-Extra: torch
Requires-Dist: torch (>=1.0) ; extra == 'torch'
Provides-Extra: torch-speech
Requires-Dist: torchaudio ; extra == 'torch-speech'
Requires-Dist: librosa ; extra == 'torch-speech'
Requires-Dist: pyctcdecode (>=0.3.0) ; extra == 'torch-speech'
Requires-Dist: phonemizer ; extra == 'torch-speech'
Provides-Extra: torchhub
Requires-Dist: filelock ; extra == 'torchhub'
Requires-Dist: huggingface-hub (<1.0,>=0.1.0) ; extra == 'torchhub'
Requires-Dist: importlib-metadata ; extra == 'torchhub'
Requires-Dist: numpy (>=1.17) ; extra == 'torchhub'
Requires-Dist: packaging (>=20.0) ; extra == 'torchhub'
Requires-Dist: protobuf ; extra == 'torchhub'
Requires-Dist: regex (!=2019.12.17) ; extra == 'torchhub'
Requires-Dist: requests ; extra == 'torchhub'
Requires-Dist: sacremoses ; extra == 'torchhub'
Requires-Dist: sentencepiece (!=0.1.92,>=0.1.91) ; extra == 'torchhub'
Requires-Dist: torch (>=1.0) ; extra == 'torchhub'
Requires-Dist: tokenizers (!=0.11.3,>=0.11.1) ; extra == 'torchhub'
Requires-Dist: tqdm (>=4.27) ; extra == 'torchhub'
Provides-Extra: vision
Requires-Dist: Pillow ; extra == 'vision'
